justbytes/__init__.py
justbytes/_config.py
justbytes/_constants.py
justbytes/_errors.py
justbytes/_generators.py
justbytes/_size.py
justbytes/_sizes.py
justbytes/version.py
justbytes-0.15.2.dist-info/LICENSE
justbytes-0.15.2.dist-info/METADATA
justbytes-0.15.2.dist-info/WHEEL
justbytes-0.15.2.dist-info/top_level.txt
justbytes-0.15.2.dist-info/RECORD
