Metadata-Version: 2.1
Name: justbytes
Version: 0.15.2
Summary: "computing with and displaying bytes"
Home-page: https://github.com/mulkieran/justbytes
Author: Anne Mulhern
Author-email: amulhern@redhat.com
License: LGPL-2.1-or-later
Platform: Linux
Classifier: Development Status :: 2 - Pre-Alpha
Classifier: Intended Audience :: Developers
Classifier: License :: OSI Approved :: GNU Lesser General Public License v2 or later (LGPLv2+)
Classifier: Operating System :: POSIX :: Linux
Classifier: Programming Language :: Python
Classifier: Programming Language :: Python :: 3
Classifier: Programming Language :: Python :: Implementation :: CPython
Classifier: Topic :: Software Development :: Libraries
Classifier: Topic :: System :: Hardware
Classifier: Topic :: System :: Operating System Kernels :: Linux
License-File: LICENSE
Requires-Dist: justbases (>=0.13)
